py_asl.py
py_asl-0.1.4.dist-info/LICENSE
py_asl-0.1.4.dist-info/METADATA
py_asl-0.1.4.dist-info/WHEEL
py_asl-0.1.4.dist-info/top_level.txt
py_asl-0.1.4.dist-info/RECORD
