Metadata-Version: 2.1
Name: py-asl
Version: 0.1.4
Summary: Python object model for the Amazon States Language
Home-page: https://github.com/aabdullah-bos/py-asl
Author: Aquil Abdullah
License: UNKNOWN
Platform: UNKNOWN
